ipxact2systemverilog/__init__.py
ipxact2systemverilog/cli.py
ipxact2systemverilog/ipxact2hdlCommon.py
ipxact2systemverilog/validate.py
ipxact2systemverilog/xml/LICENSE.md
ipxact2systemverilog/xml/README.md
ipxact2systemverilog/xml/ieee-1685-2009/README.md
ipxact2systemverilog/xml/ieee-1685-2009/abstractionDefinition.xsd
ipxact2systemverilog/xml/ieee-1685-2009/abstractor.xsd
ipxact2systemverilog/xml/ieee-1685-2009/autoConfigure.xsd
ipxact2systemverilog/xml/ieee-1685-2009/busDefinition.xsd
ipxact2systemverilog/xml/ieee-1685-2009/busInterface.xsd
ipxact2systemverilog/xml/ieee-1685-2009/commonStructures.xsd
ipxact2systemverilog/xml/ieee-1685-2009/component.xsd
ipxact2systemverilog/xml/ieee-1685-2009/configurable.xsd
ipxact2systemverilog/xml/ieee-1685-2009/constraints.xsd
ipxact2systemverilog/xml/ieee-1685-2009/design.xsd
ipxact2systemverilog/xml/ieee-1685-2009/designConfig.xsd
ipxact2systemverilog/xml/ieee-1685-2009/file.xsd
ipxact2systemverilog/xml/ieee-1685-2009/fileType.xsd
ipxact2systemverilog/xml/ieee-1685-2009/generator.xsd
ipxact2systemverilog/xml/ieee-1685-2009/identifier.xsd
ipxact2systemverilog/xml/ieee-1685-2009/index.xsd
ipxact2systemverilog/xml/ieee-1685-2009/memoryMap.xsd
ipxact2systemverilog/xml/ieee-1685-2009/model.xsd
ipxact2systemverilog/xml/ieee-1685-2009/port.xsd
ipxact2systemverilog/xml/ieee-1685-2009/signalDrivers.xsd
ipxact2systemverilog/xml/ieee-1685-2009/simpleTypes.xsd
ipxact2systemverilog/xml/ieee-1685-2009/subInstances.xsd
ipxact2systemverilog/xml/ieee-1685-2009/TGI/TGI.xsd
ipxact2systemverilog/xml/ieee-1685-2014/README.md
ipxact2systemverilog/xml/ieee-1685-2014/abstractionDefinition.xsd
ipxact2systemverilog/xml/ieee-1685-2014/abstractor.xsd
ipxact2systemverilog/xml/ieee-1685-2014/autoConfigure.xsd
ipxact2systemverilog/xml/ieee-1685-2014/busDefinition.xsd
ipxact2systemverilog/xml/ieee-1685-2014/busInterface.xsd
ipxact2systemverilog/xml/ieee-1685-2014/catalog.xsd
ipxact2systemverilog/xml/ieee-1685-2014/commonStructures.xsd
ipxact2systemverilog-1.0.29.dist-info/licenses/LICENSE
ipxact2systemverilog-1.0.29.dist-info/METADATA
ipxact2systemverilog-1.0.29.dist-info/WHEEL
ipxact2systemverilog-1.0.29.dist-info/entry_points.txt
ipxact2systemverilog-1.0.29.dist-info/top_level.txt
ipxact2systemverilog-1.0.29.dist-info/RECORD
