Metadata-Version: 2.4
Name: ipxact2systemverilog
Version: 1.0.29
Summary: Generate VHDL, SystemVerilog, html, rst, md, pdf, c headers from an IPXACT description
Author: oddball
Project-URL: Repository, https://github.com/oddball/ipxact2systemverilog
Keywords: ipxact2systemverilog,ipxact2vhdl,VHDL,SystemVerilog,html,rst,md,pdf,IPXACT
Classifier: Development Status :: 5 - Production/Stable
Classifier: Intended Audience :: Developers
Classifier: Topic :: Software Development :: Code Generators
Classifier: Topic :: Software Development :: Embedded Systems
Classifier: Programming Language :: Python :: 3
Requires-Python: >=3
License-File: LICENSE
Requires-Dist: docutils
Requires-Dist: lxml
Requires-Dist: mdutils
Requires-Dist: restructuredtext-lint
Requires-Dist: sphinx
Requires-Dist: sphinxcontrib-wavedrom
Requires-Dist: rstcloth
Dynamic: license-file
